octodns_azure/__init__.py
octodns_azure-1.0.0.dist-info/licenses/LICENSE
octodns_azure-1.0.0.dist-info/METADATA
octodns_azure-1.0.0.dist-info/WHEEL
octodns_azure-1.0.0.dist-info/top_level.txt
octodns_azure-1.0.0.dist-info/RECORD
