Metadata-Version: 2.4
Name: octodns-azure
Version: 1.0.0
Summary:  Azure DNS & TrafficManager provider for octoDNS
Home-page: https://github.com/octodns/octodns-azure
Author: Ross McFarland
Author-email: rwmcfa1@gmail.com
License: MIT
Requires-Python: >=3.9
License-File: LICENSE
Requires-Dist: azure-identity>=1.16.1
Requires-Dist: azure-mgmt-dns<8.2.0,>=8.1.0
Requires-Dist: azure-mgmt-privatedns<1.1.0,>=1.0.0
Requires-Dist: azure-mgmt-trafficmanager<1.2.0,>=1.1.0
Requires-Dist: msrestazure<0.7.0,>=0.6.4
Requires-Dist: octodns>=1.5.0
Provides-Extra: dev
Requires-Dist: pytest>=6.2.5; extra == "dev"
Requires-Dist: pytest-cov>=3.0.0; extra == "dev"
Requires-Dist: pytest-network>=0.0.1; extra == "dev"
Requires-Dist: black<25.0.0,>=24.3.0; extra == "dev"
Requires-Dist: build>=0.7.0; extra == "dev"
Requires-Dist: isort>=5.11.5; extra == "dev"
Requires-Dist: markdown-it-py>=2.2.0; extra == "dev"
Requires-Dist: pyflakes>=2.2.0; extra == "dev"
Requires-Dist: readme_renderer[md]>=26.0; extra == "dev"
Requires-Dist: twine>=3.4.2; extra == "dev"
Provides-Extra: test
Requires-Dist: pytest>=6.2.5; extra == "test"
Requires-Dist: pytest-cov>=3.0.0; extra == "test"
Requires-Dist: pytest-network>=0.0.1; extra == "test"
Dynamic: author
Dynamic: author-email
Dynamic: description
Dynamic: description-content-type
Dynamic: home-page
Dynamic: license
Dynamic: license-file
Dynamic: provides-extra
Dynamic: requires-dist
Dynamic: requires-python
Dynamic: summary
